dukeai_lib/__init__.py
dukeai_lib/application.py
dukeai_lib/globals.py
dukeai_lib/tools.py
dukeai_lib/utilities.py
dukeai_lib/load_transmission/__init__.py
dukeai_lib/load_transmission/functions.py
dukeai_lib/schema_kung_fu/__init__.py
dukeai_lib/schema_kung_fu/accessorial.py
dukeai_lib/schema_kung_fu/bill_of_lading.py
dukeai_lib/schema_kung_fu/classification.py
dukeai_lib/schema_kung_fu/classification_exceptions.py
dukeai_lib/schema_kung_fu/invoice.py
dukeai_lib/schema_kung_fu/noa_lor.py
dukeai_lib/schema_kung_fu/parse_classification_page_range.py
dukeai_lib/schema_kung_fu/rate_confirmation.py
dukeai_lib/schema_kung_fu/rsi_translator.py
dukeai_lib/schema_kung_fu/schema_utilities.py
src/__init__.py
src/application.py
src/tools.py
src/utilities.py
dukeai_lib-0.2.5.dist-info/LICENSE
dukeai_lib-0.2.5.dist-info/METADATA
dukeai_lib-0.2.5.dist-info/WHEEL
dukeai_lib-0.2.5.dist-info/top_level.txt
dukeai_lib-0.2.5.dist-info/RECORD
