Metadata-Version: 2.1
Name: dukeai-lib
Version: 0.2.5
Summary: Common functions used across the DUKE.ai project environments.
Home-page: https://duke.ai
Author: Blake Donahoo
Author-email: Blake Donahoo <blake@duke.ai>
License: GNU General Public License v3 (GPLv3)
Keywords: dukeai,duke.ai
Classifier: Programming Language :: Python :: 3.7
Classifier: Programming Language :: Python :: 3.8
Classifier: Programming Language :: Python :: 3.9
Classifier: License :: OSI Approved :: GNU General Public License v3 (GPLv3)
Classifier: Topic :: Utilities
Requires-Python: >=3.7
License-File: LICENSE
Requires-Dist: chalice ~=1.27.1
Requires-Dist: requests ~=2.27.1
Requires-Dist: base58 ==2.1.1
Requires-Dist: urllib3 ~=1.26.9
